{
  "src/txt/file01.txt": [
    "src/txt/fr-fr/file01.txt",
    "src/txt/it/file01.yml"
  ],
  "src/txt/file02.txt": [
    "src/txt/fr-fr/file02.txt",
    "src/txt/it/file02.yml"
  ],
  "src/txt/file03.txt": [
    "src/txt/fr-fr/file03.txt",
    "src/txt/it/file03.yml"
  ],
  "src/txt/file04.txt": [
    "src/txt/fr-fr/file04.txt",
    "src/txt/it/file04.yml"
  ],
  "src/txt/file05.txt": [
    "src/txt/fr-fr/file05.txt",
    "src/txt/it/file05.yml"
  ],
  "src/txt/fr": [
    "src/txt/fr-fr/fr",
    "src/txt/it/fr.yml"
  ],
  "src/txt/it-it": [
    "src/txt/fr-fr/it-it",
    "src/txt/it/it-it.yml"
  ]
}